LICENSE
MANIFEST.in
README.rst
setup.cfg
setup.py
versioneer.py
plottwist/__init__.py
plottwist/config/__init__.py
plottwist/config/__version__.py
plottwist/config/_version.py
plottwist/config/development/artellapipe-assets.yml
plottwist/config/development/artellapipe-files.yml
plottwist/config/development/artellapipe-launcher-plugins-dccselector.yml
plottwist/config/development/artellapipe-launcher.yml
plottwist/config/development/artellapipe-libs-kitsu.yml
plottwist/config/development/artellapipe-libs-usd.yml
plottwist/config/development/artellapipe-naming.yml
plottwist/config/development/artellapipe-playblasts.yml
plottwist/config/development/artellapipe-project.yml
plottwist/config/development/artellapipe-pyblishplugins.yml
plottwist/config/development/artellapipe-tools-artellamanager.yml
plottwist/config/development/artellapipe-tools-artellauploader.yml
plottwist/config/development/artellapipe-tools-assetslibrary.yml
plottwist/config/development/artellapipe-tools-assetsmanager.yml
plottwist/config/development/artellapipe-tools-bugtracker.yml
plottwist/config/development/artellapipe-tools-changelog.yml
plottwist/config/development/artellapipe-tools-dependenciesmanager.yml
plottwist/config/development/artellapipe-tools-lightrigsmanager.yml
plottwist/config/development/artellapipe-tools-modelchecker.yml
plottwist/config/development/artellapipe-tools-namemanager.yml
plottwist/config/development/artellapipe-tools-playblastmanager.yml
plottwist/config/development/artellapipe-tools-renamer.yml
plottwist/config/development/plottwist-libs-pyblish.yml
plottwist/config/development/maya/artellapipe-menu.yml
plottwist/config/production/artellapipe-assets.yml
plottwist/config/production/artellapipe-files.yml
plottwist/config/production/artellapipe-launcher-plugins-dccselector.yml
plottwist/config/production/artellapipe-launcher.yml
plottwist/config/production/artellapipe-libs-kitsu.yml
plottwist/config/production/artellapipe-libs-usd.yml
plottwist_config.egg-info/PKG-INFO
plottwist_config.egg-info/SOURCES.txt
plottwist_config.egg-info/dependency_links.txt
plottwist_config.egg-info/not-zip-safe
plottwist_config.egg-info/requires.txt
plottwist_config.egg-info/top_level.txt
