Metadata-Version: 2.1
Name: plottwist-config
Version: 0.0.18
Summary: Plot Twist Module that contains project-specific configuration files
Home-page: https://github.com/Plot-Twist-Short-Film/plottwist-config
Author: Tomas Poveda
Author-email: tpovedatd@gmail.com
License: MIT
Platform: UNKNOWN
Provides-Extra: dev
Provides-Extra: test
